{"nodes":[
{"name":"Land Allocation"},
{"name":"Food"},
{"name":"Processing"},
{"name":"Feed"},
{"name":"Other"},
{"name":"Waste"},
{"name":"Cereal Production"},
{"name":"Starchy Roots Production"},
{"name":"Oil Crops Production"},
{"name":"Pulses Production"},
{"name":"Nuts Production"},
{"name":"Vegetables Production"},
{"name":"Fruits Production"},
{"name":"Sugar Crops Production"},
{"name":"Stimulants Production"},
{"name":"Spices Production"},
{"name":"Fibers Production"},
{"name":"Tobacco Production"},
{"name":"Rubber Production"},
{"name":"Fodder Production"},
{"name":"Cereal Yield"},
{"name":"Starchy Roots Yield"},
{"name":"Oil Crops Yield"},
{"name":"Pulses Yield"},
{"name":"Nuts Yield"},
{"name":"Vegetables Yield"},
{"name":"Fruits Yield"},
{"name":"Sugar Crops Yield"},
{"name":"Stimulants Yield"},
{"name":"Spices Yield"},
{"name":"Fibers Yield"},
{"name":"Tobacco Yield"},
{"name":"Rubber Yield"},
{"name":"Fodder Yield"},
{"name":"Vegetable Oils"},
{"name":"Oil Cakes"},
{"name":"Sugar"},
{"name":"Alcohol"}, 
{"name":"Open Range Land"}, 
{"name":"Meat Production"}, 
{"name":"Fats Production"}, 
{"name":"Hides and Skins Production"}, 
{"name":"Milk, Primary Production"}, 
{"name":"Eggs Production"}, 
{"name":"Honey Production"}, 
{"name":"Wool & Hair Production"},
{"name":"Silk Production"},
{"name":"Animals"},
{"name":"Food- Animal"},
{"name":"Processing- Animal"},
{"name":"Feed- Animal"},
{"name":"Other- Animal"},
{"name":"Waste- Animal"}, 
{"name":"Primary Imports"}, 
{"name":"Primary Exports"}, 
{"name":"Processing Imports"}, 
{"name":"Processing Exports"}
],

"links":[
{"source":0,"target":20,"value":692997.61},
{"source":0,"target":21,"value":16242.73},
{"source":0,"target":22,"value":228457.19},
{"source":0,"target":23,"value":140656.28},
{"source":0,"target":24,"value":7653.42},
{"source":0,"target":25,"value":43194.17},
{"source":0,"target":26,"value":38222.13},
{"source":0,"target":27,"value":28070.65},
{"source":0,"target":28,"value":6020.71},
{"source":0,"target":29,"value":14070.51},
{"source":0,"target":30,"value":7343.72},
{"source":0,"target":31,"value":2767.28},
{"source":0,"target":32,"value":2842.24},
{"source":0,"target":33,"value":71876.64},

{"source":20,"target":6,"value":360143},
{"source":21,"target":7,"value":74774},
{"source":22,"target":8,"value":64693},
{"source":23,"target":9,"value":19387},
{"source":24,"target":10,"value":1526},
{"source":25,"target":11,"value":137263},
{"source":26,"target":12,"value":91098},
{"source":27,"target":13,"value":406531},
{"source":28,"target":14,"value":1824},
{"source":29,"target":15,"value":5217},
{"source":30,"target":16,"value":14204.702},
{"source":31,"target":17,"value":1044.62},
{"source":32,"target":18,"value":964.195},
{"source":33,"target":19,"value":121745.755},

{"source":6,"target":1,"value":263382},
{"source":7,"target":1,"value":54412},
{"source":8,"target":1,"value":9824},
{"source":9,"target":1,"value":19632},
{"source":10,"target":1,"value":2174},
{"source":11,"target":1,"value":125271},
{"source":12,"target":1,"value":78351},
{"source":14,"target":1,"value":17695},
{"source":15,"target":1,"value":1290},
{"source":16,"target":1,"value":4622},

{"source":6,"target":2,"value":1142},
{"source":7,"target":2,"value":19},
{"source":8,"target":2,"value":42302},
{"source":11,"target":2,"value":42},
{"source":12,"target":2,"value":379},
{"source":13,"target":2,"value":352702},
{"source":17,"target":2,"value":-177.272},

{"source":6,"target":3,"value":27053},
{"source":7,"target":3,"value":1630},
{"source":8,"target":3,"value":7006},
{"source":9,"target":3,"value":2131},
{"source":11,"target":3,"value":1742},
{"source":12,"target":3,"value":229},
{"source":13,"target":3,"value":6952},

{"source":6,"target":4,"value":3410},
{"source":7,"target":4,"value":306},
{"source":8,"target":4,"value":416},
{"source":9,"target":4,"value":20},
{"source":10,"target":4,"value":15},
{"source":11,"target":4,"value":298},
{"source":12,"target":4,"value":14},
{"source":13,"target":4,"value":21},
{"source":15,"target":4,"value":21},
{"source":16,"target":4,"value":11973.433},
{"source":17,"target":4,"value":962.545},
{"source":18,"target":4,"value":1088.468},

{"source":6,"target":5,"value":19059},
{"source":7,"target":5,"value":13370},
{"source":8,"target":5,"value":2133},
{"source":9,"target":5,"value":790},
{"source":10,"target":5,"value":26},
{"source":11,"target":5,"value":8168},
{"source":12,"target":5,"value":11581},
{"source":13,"target":5,"value":5414},
{"source":14,"target":5,"value":19},
{"source":15,"target":5,"value":157},
{"source":17,"target":5,"value":83.165},

{"source":2,"target":34,"value":10640},
{"source":2,"target":35,"value":27667.129},
{"source":2,"target":36,"value":50532.863},
{"source":2,"target":37,"value":7628},

{"source":34,"target":1,"value":14367},
{"source":34,"target":4,"value":8068},

{"source":35,"target":3,"value":21110.486},
{"source":35,"target":4,"value":24.695},

{"source":36,"target":1,"value":34984},
{"source":36,"target":3,"value":1327.744},
{"source":36,"target":4,"value":15484.035},
{"source":36,"target":5,"value":1},

{"source":37,"target":1,"value":3805},
{"source":37,"target":4,"value":3524},

{"source":38,"target":19,"value":3600}, 
{"source":19,"target":3,"value":121745.755}, 

{"source":3,"target":47,"value":264792.9489},

{"source":47,"target":39,"value":14157},
{"source":47,"target":40,"value":544},
{"source":47,"target":41,"value":2081.738},
{"source":47,"target":42,"value":187873},
{"source":47,"target":43,"value":4973},
{"source":47,"target":44,"value":76},
{"source":47,"target":45,"value":369.435},
{"source":47,"target":46,"value":204.24},

{"source":39,"target":48,"value":13218},
{"source":39,"target":49,"value":9},
{"source":39,"target":50,"value":8},
{"source":39,"target":51,"value":206},
{"source":39,"target":52,"value":39}, 

{"source":40,"target":48,"value":421},
{"source":40,"target":51,"value":292},

{"source":41,"target":49,"value":0.001},
{"source":41,"target":51,"value":1935.609}, 
{"source":41,"target":52,"value":164.714}, 

{"source":42,"target":48,"value":151968},
{"source":42,"target":50,"value":29612},
{"source":42,"target":51,"value":126},
{"source":42,"target":52,"value":8642}, 

{"source":43,"target":48,"value":4127},
{"source":43,"target":50,"value":54},
{"source":43,"target":51,"value":73},
{"source":43,"target":52,"value":475}, 

{"source":44,"target":48,"value":47},

{"source":45,"target":51,"value":407.851},

{"source":46,"target":51,"value":210.276},

{"source":49,"target":48,"value":9.001}, 

{"source":53,"target":6,"value":13138},
{"source":53,"target":7,"value":724},
{"source":53,"target":8,"value":1640},
{"source":53,"target":9,"value":4558},
{"source":53,"target":10,"value":1271},
{"source":53,"target":11,"value":1700},
{"source":53,"target":12,"value":2746},
{"source":53,"target":14,"value":11128},
{"source":53,"target":15,"value":381},
{"source":53,"target":16,"value":1183.189},
{"source":53,"target":17,"value":63.824},
{"source":53,"target":18,"value":205.082}, 

{"source":53,"target":39,"value":463},
{"source":53,"target":40,"value":176},
{"source":53,"target":41,"value":69.332},
{"source":53,"target":42,"value":2798},
{"source":53,"target":43,"value":55},
{"source":53,"target":44,"value":1},
{"source":53,"target":45,"value":87.197},
{"source":53,"target":46,"value":6.001},

{"source":6,"target":54,"value":24073},
{"source":7,"target":54,"value":931},
{"source":8,"target":54,"value":2034},
{"source":9,"target":54,"value":339},
{"source":10,"target":54,"value":583},
{"source":11,"target":54,"value":3414},
{"source":12,"target":54,"value":2868},
{"source":14,"target":54,"value":1064},
{"source":15,"target":54,"value":722},
{"source":16,"target":54,"value":3711.774},
{"source":17,"target":54,"value":269.23},
{"source":18,"target":54,"value":80.809},

{"source":39,"target":54,"value":1141},
{"source":40,"target":54,"value":6},
{"source":41,"target":54,"value":64.711},
{"source":42,"target":54,"value":349},
{"source":43,"target":54,"value":69},
{"source":44,"target":54,"value":31},
{"source":45,"target":54,"value":20.171},
{"source":45,"target":54,"value":2.898},

{"source":55,"target":34,"value":12963},
{"source":55,"target":35,"value":1078.575},
{"source":55,"target":36,"value":4290.227},
{"source":55,"target":37,"value":297},

{"source":34,"target":56,"value":788},
{"source":35,"target":56,"value":8055.727},
{"source":36,"target":56,"value":3589.314},
{"source":37,"target":56,"value":542}


]}